enqueue/__init__.py
enqueue-0.1.0.dist-info/licenses/LICENSE
enqueue-0.1.0.dist-info/METADATA
enqueue-0.1.0.dist-info/WHEEL
enqueue-0.1.0.dist-info/top_level.txt
enqueue-0.1.0.dist-info/RECORD
